Metadata-Version: 1.1
Name: pygithubctl
Version: 2.7.23
Summary: The GitHub command-line tool, pygithubctl
Home-page: http://github.com/sarathkumarsivan/pygithubctl
Author: Sarath Kumar Sivan
Author-email: sarathkumarsivan@gmail.com
License: MIT
Keywords: pygithubctl githubctl
Platform: UNKNOWN
Classifier: Development Status :: 5 - Production/Stable
Classifier: Environment :: Console
Classifier: Intended Audience :: Developers
Classifier: License :: OSI Approved :: MIT License
Classifier: Natural Language :: English
Classifier: Programming Language :: Python :: 2.7
Classifier: Programming Language :: Python :: 3.4
Classifier: Programming Language :: Python :: 3.5
Classifier: Programming Language :: Python :: 3.6
